FramesViewer/__init__.py
FramesViewer/camera.py
FramesViewer/inputs.py
FramesViewer/mesh.py
FramesViewer/utils.py
FramesViewer/viewer.py
framesviewer-1.1.0.dist-info/licenses/LICENSE.txt
framesviewer-1.1.0.dist-info/METADATA
framesviewer-1.1.0.dist-info/WHEEL
framesviewer-1.1.0.dist-info/top_level.txt
framesviewer-1.1.0.dist-info/RECORD
