Metadata-Version: 2.4
Name: FramesViewer
Version: 1.1.0
Summary: A simple live 6D frames viewer (and more)
Author-email: Antoine Pirrone <antoine.pirrone@gmail.com>
Requires-Python: >=3.8
License-File: LICENSE.txt
Requires-Dist: numpy
Requires-Dist: PyOpenGL
Requires-Dist: scipy
Requires-Dist: pywavefront
Dynamic: license-file
